<?xml version="1.0" encoding="UTF-8" ?>


<data.xml>
	<kColl id="rootKColl" />
	<kColl id="APPChannelKColl" />
	<kColl id="APPSessionKColl">
		<field id="EMP_SID" />
		<field id="currentUserId" />
		<field id="orgid" />
		<field id="organNo" />
		<field id="menuId" />
		<field id="actorname" />
		<field id="ARTI_ORGANNO" />
		<field id="OPENDAY" />
		<field id="LAST_OPENDAY" />
		<field id="loginuserid" />
		<field id="loginusername" />
		<field id="loginorgid" />
		<field id="loginorgname" />
	</kColl>
</data.xml>