<?xml version="1.0" encoding="UTF-8" ?>


<CcrBizModel.xml>
	<TableModel id="CcrBizModel" cnname="行业数据模型" dbTableName="ccr_biz_model">
		<Field id="com_cll_typ" isPK="true" columnName="com_cll_typ" cnname="行业类型" length="5" JDBCType="VARCHAR2" canBeNull="false"/>
		<Field id="com_opt_scale" isPK="true" columnName="com_opt_scale" cnname="企业规模" length="2" JDBCType="VARCHAR2" canBeNull="false"/>
		<Field id="index_no" isPK="true" columnName="index_no" cnname="指标编号" length="12" JDBCType="VARCHAR2" canBeNull="false"/>
		<Field id="index_name" columnName="index_name" cnname="指标名称" length="60" JDBCType="VARCHAR2" canBeNull="true"/>
		<Field id="excellent_score" columnName="excellent_score" cnname="优秀值" length="16" JDBCType="NUMBER" canBeNull="true"/>
		<Field id="good_score" columnName="good_score" cnname="良好值" length="16" JDBCType="NUMBER" canBeNull="true"/>
		<Field id="average_score" columnName="average_score" cnname="平均值" length="16" JDBCType="NUMBER" canBeNull="true"/>
		<Field id="lower_score" columnName="lower_score" cnname="较低值" length="16" JDBCType="NUMBER" canBeNull="true"/>
		<Field id="worse_score" columnName="worse_score" cnname="较差值" length="16" JDBCType="NUMBER" canBeNull="true"/>
		<Field id="worst_score" columnName="worst_score" cnname="最差值" length="16" JDBCType="NUMBER" canBeNull="true"/>
	</TableModel>
</CcrBizModel.xml>