<?xml version="1.0" encoding='GB18030'?>
<rule-set name="S_DUTY">

<java:import>java.lang.Object</java:import>
<java:import>java.lang.String</java:import>
<java:import>java.util.Map</java:import>
<java:import>com.ecc.emp.core.Context</java:import>
<java:import>com.ecc.shuffle.common.Utils</java:import>

<db:columns>type</db:columns>

<rule name="query" salience="1" isolation="yes">
<parameter identifier="context">
	<class>com.ecc.emp.core.Context</class>
</parameter>
<parameter identifier="paramMap">
	<class>java.util.HashMap</class>
</parameter>
<java:condition>true</java:condition>

<java:consequence>
		if(context.getDataValue("currentUserId").toString().equals("admin")){
			paramMap.put("_result_","1=1");
		}else{
			paramMap.put("_result_","1=1");
		}
		
</java:consequence>
</rule>

<rule name="update" salience="2" isolation="yes">
<parameter identifier="context">
	<class>com.ecc.emp.core.Context</class>
</parameter>
<parameter identifier="paramMap">
	<class>java.util.HashMap</class>
</parameter>
<java:condition>true</java:condition>

<java:consequence>
		if(context.getDataValue("currentUserId").toString().equals("admin")){
			paramMap.put("_result_","1=1");
		}else{
			paramMap.put("_result_","1=1");
		}
</java:consequence>
</rule>

<rule name="delete" salience="2" isolation="yes">
<parameter identifier="context">
	<class>com.ecc.emp.core.Context</class>
</parameter>
<parameter identifier="paramMap">
	<class>java.util.HashMap</class>
</parameter>
<java:condition>true</java:condition>

<java:consequence> 
    if("0".equals(paramMap.get("type").toString()))
			paramMap.put("_result_","1=2");
		else{
			if(context.getDataValue("currentUserId").toString().equals("test")){
				paramMap.put("_result_","1=1");
			}else{
				paramMap.put("_result_","1=2");
			}
    }
</java:consequence>
</rule>

</rule-set>

