<?xml version="1.0" encoding="UTF-8" ?>


<MortCarPledgeInsurance.xml>
	<TableModel id="MortCarPledgeInsurance" cnname="汽车履约保证保险、出口信用保证保险" dbTableName="mort_car_pledge_insurance">
		<Field id="car_insure_id" isPK="true" columnName="car_insure_id" cnname="汽车保险编号" length="20" JDBCType="VARCHAR2" canBeNull="false"/>
		<Field id="guaranty_no" columnName="guaranty_no" cnname="押品编号" length="40" JDBCType="VARCHAR2" canBeNull="false"/>
		<Field id="insure_org_name" columnName="insure_org_name" cnname="保险机构" length="100" JDBCType="VARCHAR2" canBeNull="true"/>
		<Field id="insurance_type_cd" columnName="insurance_type_cd" cnname="险种" length="20" JDBCType="VARCHAR2" canBeNull="true"/>
		<Field id="policy_holder" columnName="policy_holder" cnname="投保人" length="100" JDBCType="VARCHAR2" canBeNull="true"/>
		<Field id="beneficiary_name" columnName="beneficiary_name" cnname="受益人" length="100" JDBCType="VARCHAR2" canBeNull="true"/>
		<Field id="start_date" columnName="start_date" cnname="起始日期" length="10" JDBCType="CHAR" canBeNull="true"/>
		<Field id="expire_date" columnName="expire_date" cnname="到期日期" length="10" JDBCType="CHAR" canBeNull="true"/>
		<Field id="effective_date" columnName="effective_date" cnname="生效日期" length="10" JDBCType="CHAR" canBeNull="true"/>
		<Field id="sys_update_time" columnName="sys_update_time" cnname="更新日期" length="10" JDBCType="CHAR" canBeNull="true"/>
		<Field id="handling_user" columnName="handling_user" cnname="更新人" length="40" JDBCType="VARCHAR2" canBeNull="true"/>
		<Field id="insur_no" columnName="insur_no" cnname="保险单号" length="100" JDBCType="VARCHAR2" canBeNull="true"/>
		<Field id="insure_count" columnName="insure_count" cnname="份数" length="38" JDBCType="NUMBER" canBeNull="true"/>
		<Field id="insu_ccr" columnName="insu_ccr" cnname="投保币种" length="3" JDBCType="CHAR" canBeNull="true"/>
		<Field id="insu_amt" columnName="insu_amt" cnname="投保金额" length="20" JDBCType="NUMBER" canBeNull="true"/>
		<Field id="memo" columnName="memo" cnname="备注" length="1000" JDBCType="VARCHAR2"/>
	</TableModel>
</MortCarPledgeInsurance.xml>