<?xml version="1.0" encoding="UTF-8" ?>


<IqpFastCreditDscnt.xml>
	<TableModel id="IqpFastCreditDscnt" cnname="远期信用证项下汇票贴现从表" dbTableName="iqp_fast_credit_dscnt">
		<Field id="serno" isPK="true" columnName="serno" cnname="业务编号" length="40" JDBCType="VARCHAR2" canBeNull="false"/>
		<Field id="is_replace" columnName="is_replace" cnname="是否置换" length="1" JDBCType="CHAR" canBeNull="true"/>
		<Field id="rpled_serno" columnName="rpled_serno" cnname="被置换业务编号" length="40" JDBCType="VARCHAR2" canBeNull="true"/>
		<Field id="bank_bp_no" columnName="bank_bp_no" cnname="我行bp号" length="40" JDBCType="VARCHAR2" canBeNull="true"/>
		<Field id="is_internal_cert" columnName="is_internal_cert" cnname="是否国内证项下" length="1" JDBCType="CHAR" canBeNull="true"/>
		<Field id="post_order_no" columnName="post_order_no" cnname="汇票号码" length="40" JDBCType="VARCHAR2" canBeNull="true"/>
		<Field id="bill_cur_type" columnName="bill_cur_type" cnname="票据币种" length="3" JDBCType="CHAR" canBeNull="true"/>
		<Field id="drft_amt" columnName="drft_amt" cnname="票面金额" length="16" JDBCType="NUMBER" canBeNull="true"/>
		<Field id="issue_date" columnName="issue_date" cnname="出票日期" length="10" JDBCType="VARCHAR2" canBeNull="true"/>
		<Field id="bill_end_date" columnName="bill_end_date" cnname="票据到期日" length="10" JDBCType="VARCHAR2" canBeNull="true"/>
		<Field id="drwr_name" columnName="drwr_name" cnname="出票人名称" length="80" JDBCType="VARCHAR2" canBeNull="true"/>
		<Field id="accptr_name" columnName="accptr_name" cnname="承兑人名称" length="80" JDBCType="VARCHAR2" canBeNull="true"/>
		<Field id="dscnt_date" columnName="dscnt_date" cnname="贴现日期" length="10" JDBCType="VARCHAR2" canBeNull="true"/>
		<Field id="dscnt_day" columnName="dscnt_day" cnname="贴现天数" length="38" JDBCType="NUMBER" canBeNull="true"/>
		<Field id="arrangr_deduct" columnName="arrangr_deduct" cnname="预扣款项" length="16" JDBCType="NUMBER" canBeNull="true"/>
		<Field id="pay_amt" columnName="pay_amt" cnname="实付金额" length="16" JDBCType="NUMBER" canBeNull="true"/>
		<Field id="biz_settl_mode" columnName="biz_settl_mode" cnname="原业务结算方式" length="5" JDBCType="VARCHAR2" canBeNull="true"/>
		<Field id="fount_fin_advice" columnName="fount_fin_advice" cnname="原国业部融资意见" length="250" JDBCType="VARCHAR2" canBeNull="true"/>
	</TableModel>
</IqpFastCreditDscnt.xml>