<?xml version="1.0" encoding="UTF-8"?>
<actionDefines>
	<classMap>
		<map id="action" class="com.yucheng.cmis.ad.mvc.ADRequestController"/>
		<map id="flowInvoker" class="com.yucheng.cmis.ad.mvc.ADFlowInvoker"/>
		<map id="outputViews" class="java.util.HashMap"/>
		<map id="output" class="com.ecc.emp.data.KeyedCollection"/>
		<map id="kColl" class="com.ecc.emp.data.KeyedCollection"/>
		<map id="iColl" class="com.ecc.emp.data.IndexedCollection"/>
		<map id="field" class="com.ecc.emp.data.DataField"/>
	</classMap>
	
	<!-- 获取操作主页面 -->
	<action id="queryIqpChkStoreTaskList" type="normal" checkSession="true" >
		<flowInvoker>
			<operation class="com.yucheng.cmis.biz01line.iqp.op.iqpchkstoretask.QueryIqpChkStoreTaskListOp"/>
			<transition dest="retPage"/>
		</flowInvoker>
		<outputViews>
			<jspView id="retPage" url="biz01line/iqp/IqpChkStoreTask/queryIqpChkStoreTaskList.jsp" />
		</outputViews>
	</action>
	
	<!-- 获得编辑页面 -->
	<action id="getIqpChkStoreTaskUpdatePage" type="normal" checkSession="true" >
		<flowInvoker>
			<operation updateCheck="false" class="com.yucheng.cmis.biz01line.iqp.op.iqpchkstoretask.QueryIqpChkStoreTaskDetailOp"/>
			<transition dest="retPage"/>
		</flowInvoker>
		<outputViews>
			<jspView id="retPage" url="biz01line/iqp/IqpChkStoreTask/updateIqpChkStoreTaskRecord.jsp" />
		</outputViews>
	</action>
	
	<!-- 更新记录 -->
	<action id="updateIqpChkStoreTaskRecord" type="normal" checkSession="true" >
		<flowInvoker>
			<operation class="com.yucheng.cmis.biz01line.iqp.op.iqpchkstoretask.UpdateIqpChkStoreTaskRecordOp"/>
			<transition dest="retPage"/>
		</flowInvoker>
		<outputViews>
			<view id="retPage" class="com.yucheng.cmis.view.JSONView">
				<output class="com.ecc.emp.data.KeyedCollection">
					<field id="flag" class="com.ecc.emp.data.DataField" />
				</output>
			</view>
		</outputViews>
	</action>
	
	
	<!-- 获得查看页面 -->
	<action id="getIqpChkStoreTaskViewPage" type="normal" checkSession="true" >
		<flowInvoker>
			<operation class="com.yucheng.cmis.biz01line.iqp.op.iqpchkstoretask.QueryIqpChkStoreTaskDetailOp"/>
			<transition dest="updatePage"/>
		</flowInvoker>
		<outputViews>
			<jspView id="updatePage" url="biz01line/iqp/IqpChkStoreTask/queryIqpChkStoreTaskDetail.jsp" />
		</outputViews>
	</action>
	
	<!-- 获得新增页面 -->
	<action id="getIqpChkStoreTaskAddPage" type="normal" checkSession="true" >
		<jspView id="addPage" url="biz01line/iqp/IqpChkStoreTask/addIqpChkStoreTaskRecord.jsp"/>
	</action>
	
	<!-- 新增记录 -->
	<action id="addIqpChkStoreTaskRecord" type="normal" checkSession="true" >
		<flowInvoker>
			<operation class="com.yucheng.cmis.biz01line.iqp.op.iqpchkstoretask.AddIqpChkStoreTaskRecordOp"/>
			<transition dest="retPage"/>
		</flowInvoker>
		<outputViews>
			<view id="retPage" class="com.yucheng.cmis.view.JSONView">
				<output class="com.ecc.emp.data.KeyedCollection">
					<field id="flag" class="com.ecc.emp.data.DataField" />
				</output>
			</view>
		</outputViews>
	</action>	
	
	<!-- 删除记录 -->
	<action id="deleteIqpChkStoreTaskRecord" type="normal" checkSession="true" >
		<flowInvoker>
			<operation class="com.yucheng.cmis.biz01line.iqp.op.iqpchkstoretask.DeleteIqpChkStoreTaskRecordOp"/>
			<transition dest="retPage"/>
		</flowInvoker>
		<outputViews>
			<view id="retPage" class="com.yucheng.cmis.view.JSONView">
				<output class="com.ecc.emp.data.KeyedCollection">
					<field id="flag" class="com.ecc.emp.data.DataField" />
				</output>
			</view>
		</outputViews>
	</action>
	
	<!-- 分页查询记录列表 -->
		<action id="pageIqpChkStoreTaskQuery" type="normal" checkSession="true" >
		<flowInvoker>
			<operation class="com.yucheng.cmis.biz01line.iqp.op.iqpchkstoretask.QueryIqpChkStoreTaskListOp"/>
			<transition dest="queryListRes"/>
		</flowInvoker>
		<outputViews>
			<jsonView class="com.yucheng.cmis.view.JSONView" id="queryListRes">
				<output>
					<iColl id="IqpChkStoreTaskList">
						<kColl>
						</kColl>
					</iColl>
					<kColl id="pageInfo">
						<field id="currentPage" />
						<field id="maxLine" />
						<field id="recordSize" />
					</kColl>
				</output>
			</jsonView>
		</outputViews>
	</action>
	
	<!-- 获得查看页面 -->
	<action id="getIqpOverseeAgrViewTabForChkPage" type="normal" checkSession="true" >
		<flowInvoker>
			<operation class="com.yucheng.cmis.biz01line.iqp.op.iqpchkstoretask.QueryIqpOverseeAgrDetailTabForChkOp"/>
			<transition dest="updatePage"/>
		</flowInvoker>
		<outputViews>
			<jspView id="updatePage" url="biz01line/iqp/IqpChkStoreTask/queryIqpOverseeAgrDetailTabForChk.jsp" />
		</outputViews>
	</action>
	
	<!-- 获得编辑页面 -->
	<action id="getIqpChkStoreTaskRecordTabPage" type="normal" checkSession="true" >
		<flowInvoker>
			<operation updateCheck="false" class="com.yucheng.cmis.biz01line.iqp.op.iqpchkstoretask.QueryIqpChkStoreTaskRecordTabOp"/>
			<transition dest="retPage"/>
		</flowInvoker>
		<outputViews>
			<jspView id="retPage" url="biz01line/iqp/IqpChkStoreTask/updateIqpChkStoreTaskRecordTab.jsp" />
		</outputViews>
	</action>
	
	<!-- 获得编辑页面(查看) -->
	<action id="getIqpChkStoreTaskRecordTabViewPage" type="normal" checkSession="true" >
		<flowInvoker>
			<operation updateCheck="false" class="com.yucheng.cmis.biz01line.iqp.op.iqpchkstoretask.QueryIqpChkStoreTaskRecordTabOp"/>
			<transition dest="retPage"/>
		</flowInvoker>
		<outputViews>
			<jspView id="retPage" url="biz01line/iqp/IqpChkStoreTask/queryIqpChkStoreTaskRecordTab.jsp" />
		</outputViews>
	</action>
	
	<!-- 生成任务前校验当天是否已存在任务 -->
	<action id="checkIqpChkStoreTask" type="normal" checkSession="true" >
		<flowInvoker>
			<operation class="com.yucheng.cmis.biz01line.iqp.op.iqpchkstoretask.CheckIqpChkStoreTaskOp"/>
			<transition dest="retPage"/>
		</flowInvoker>
		<outputViews>
			<view id="retPage" class="com.yucheng.cmis.view.JSONView">
				<output class="com.ecc.emp.data.KeyedCollection">
					<field id="flag" class="com.ecc.emp.data.DataField" />
					<field id="msg" class="com.ecc.emp.data.DataField" />
				</output>
			</view>
		</outputViews>
	</action>
	
	<!-- 获取操作主页面 -->
	<action id="queryIqpOverseeUnderstorePopForChkList" type="normal" checkSession="true" >
		<flowInvoker>
			<operation class="com.yucheng.cmis.biz01line.iqp.op.iqpchkstoretask.QueryIqpOverseeUnderstorePopForChkListOp"/>
			<transition dest="retPage"/>
		</flowInvoker>
		<outputViews>
			<jspView id="retPage" url="biz01line/iqp/IqpChkStoreTask/queryIqpOverseeUnderstorePopForChkList.jsp" />
		</outputViews>
	</action>
	
	<!-- 分页查询记录列表 -->
		<action id="pageIqpOverseeUnderstorePopForChkQuery" type="normal" checkSession="true" >
		<flowInvoker>
			<operation class="com.yucheng.cmis.biz01line.iqp.op.iqpchkstoretask.QueryIqpOverseeUnderstorePopForChkListOp"/>
			<transition dest="queryListRes"/>
		</flowInvoker>
		<outputViews>
			<jsonView class="com.yucheng.cmis.view.JSONView" id="queryListRes">
				<output>
					<iColl id="IqpOverseeUnderstoreList">
						<kColl>
						</kColl>
					</iColl>
					<kColl id="pageInfo">
						<field id="currentPage" />
						<field id="maxLine" />
						<field id="recordSize" />
					</kColl>
				</output>
			</jsonView>
		</outputViews>
	</action>
	
	<!-- 更新记录 -->
	<action id="updateIqpChkStoreTaskRecordRecord" type="normal" checkSession="true" >
		<flowInvoker>
			<operation class="com.yucheng.cmis.biz01line.iqp.op.iqpchkstoretask.UpdateIqpChkStoreTaskRecordRecordOp"/>
			<transition dest="retPage"/>
		</flowInvoker>
		<outputViews>
			<view id="retPage" class="com.yucheng.cmis.view.JSONView">
				<output class="com.ecc.emp.data.KeyedCollection">
					<field id="flag" class="com.ecc.emp.data.DataField" />
				</output>
			</view>
		</outputViews>
	</action>
	
	<!-- 查找数量和价值 -->
	<action id="queryQntValue4TaskId" type="normal" checkSession="true" >
		<flowInvoker>
			<operation class="com.yucheng.cmis.biz01line.iqp.op.iqpchkstoretask.QueryQntValue4TaskIdOp"/>
			<transition dest="retPage"/>
		</flowInvoker>
		<outputViews>
			<view id="retPage" class="com.yucheng.cmis.view.JSONView">
				<output class="com.ecc.emp.data.KeyedCollection">
					<field id="flag" class="com.ecc.emp.data.DataField" />
					<field id="qnt" class="com.ecc.emp.data.DataField" />
					<field id="value" class="com.ecc.emp.data.DataField" />
				</output>
			</view>
		</outputViews>
	</action>
</actionDefines>



